[
  {
    "id": "kompor-gas",
    "title": "Servis Kompor Gas",
    "katogori": [
      "KOMPOR",
      "PENCUCIAN",
      "TROLLY MAKAN NETAL DAN PEMANAS"
    ],
    "subtitle": {
      "KOMPOR": "<p class=\"m-0\">(KOMPOR, OVEN, 3 DECK, BOILING, BAINMARIE DLL)</p>",
      "PENCUCIAN": "<p class=\"m-0\">(DISWASH, SINK DLL)</p>"
    },
    "description": {
      "KOMPOR": "<h4>Masalah & Penanganan Kompor</h4><ol><li><strong>Kompor Tidak Menyala</strong><ul><li>Cek stop kran gas, pastikan posisi <strong>ON</strong>.</li><li>Cek tekanan gas. Jika nol, ganti tabung.</li><li>Cek regulator. Jika nol, ganti tabung.</li><li>Jika stop kran rusak, ganti baru (oleh Teknisi Distributor).</li></ul></li><li><strong>Tercium Aroma Gas Menyengat</strong><ul><li>Sistem gas sentral: alarm berbunyi & kran otomatis nutup.</li><li>Sistem tabung gas: matikan kompor.</li><li>Oles air sabun ke selang. Kalau ada gelembung, ganti selang.</li></ul></li><li><strong>Api Berwarna Merah</strong><ul><li>Burner kotor, bersihkan rutin.</li><li>Kalau berat, panggil teknisi.</li></ul></li><li><strong>Api Tidak Bisa Standby</strong><ul><li>Bersihkan & kencangkan thermocouple.</li><li>Kalau rusak, ganti baru.</li></ul></li></ol>",
      "PENCUCIAN": "<h4>Perawatan & Troubleshooting Dishwasher</h4>\n<p><strong>Menjamin Performa Optimal dan Keamanan Operasional</strong></p>\n<p>Mesin pencuci piring industri (dishwasher) di dapur rumah sakit berperan penting dalam menjaga higienitas peralatan makan dan masak. Agar tetap berfungsi maksimal, diperlukan pemeliharaan berkala serta penanganan tepat bila muncul gangguan atau alarm peringatan.</p>\n\n<h4>Permasalahan & Solusi Umum Dishwasher:</h4>\n<ol>\n  <li><strong>Tidak Ada Listrik</strong>\n    <ul>\n      <li>Pastikan dishwasher terhubung ke sumber listrik.</li>\n      <li>Periksa saklar listrik, pastikan dalam posisi ON.</li>\n    </ul>\n  </li>\n  <li><strong>Alarm AL 01 – Waktu Pengisian Air Boiler Habis</strong>\n    <ul>\n      <li>Cek pressure switch boiler, ganti jika rusak (oleh teknisi).</li>\n      <li>Pastikan stopkran air bersih terbuka.</li>\n    </ul>\n  </li>\n  <li><strong>Alarm AL 02 – Waktu Pengisian Air Tangki Habis</strong>\n    <ul>\n      <li>Periksa selang pembuangan, pastikan posisinya benar.</li>\n      <li>Bersihkan filter tangki dari kotoran.</li>\n      <li>Cek kondisi pompa drain, ganti jika rusak (oleh teknisi).</li>\n    </ul>\n  </li>\n  <li><strong>Alarm AL 03 – Waktu Pemanasan Air Boiler Habis</strong>\n    <ul>\n      <li>Cek koneksi kabel boiler ke elemen pemanas.</li>\n      <li>Periksa elemen pemanas (heater); ganti jika rusak (oleh teknisi).</li>\n    </ul>\n  </li>\n  <li><strong>Alarm AL 04 – Waktu Pemanasan Air Tangki Habis</strong>\n    <ul>\n      <li>Sama dengan penanganan AL 03: cek kabel & elemen pemanas.</li>\n    </ul>\n  </li>\n  <li><strong>Alarm AL 05 – Suhu Boiler Terlalu Panas</strong>\n    <ul>\n      <li>Periksa sensor suhu boiler, ganti jika rusak (oleh teknisi).</li>\n    </ul>\n  </li>\n  <li><strong>Alarm AL 06 – Suhu Tangki Terlalu Panas</strong>\n    <ul>\n      <li>Periksa sensor suhu tangki, ganti jika rusak (oleh teknisi).</li>\n    </ul>\n  </li>\n  <li><strong>Alarm AL 07 – Air Tangki Terlalu Penuh</strong>\n    <ul>\n      <li>Periksa selang pembuangan, pastikan tidak tersumbat.</li>\n      <li>Bersihkan filter tangki.</li>\n      <li>Cek pompa drain, ganti jika rusak (oleh teknisi).</li>\n    </ul>\n  </li>\n  <li><strong>Alarm AL 08 – Sensor NTC Tangki Error</strong>\n    <ul>\n      <li>Periksa koneksi kabel sensor NTC tangki.</li>\n      <li>Ganti sensor NTC jika rusak (oleh teknisi).</li>\n    </ul>\n  </li>\n  <li><strong>Alarm AL 09 – Sensor NTC Tangki Arus Singkat</strong>\n    <ul>\n      <li>Sama dengan AL 08: cek kabel & ganti sensor NTC jika perlu.</li>\n    </ul>\n  </li>\n  <li><strong>Alarm AL 10 – Sensor NTC Boiler Error</strong>\n    <ul>\n      <li>Periksa koneksi kabel sensor NTC boiler.</li>\n      <li>Ganti sensor NTC jika rusak (oleh teknisi).</li>\n    </ul>\n  </li>\n</ol>\n\n<h4>Rekomendasi Perawatan Berkala:</h4>\n<ul>\n  <li>✔ Pembersihan filter setiap minggu.</li>\n  <li>✔ Cek koneksi kabel & selang setiap bulan.</li>\n  <li>✔ Kalibrasi sensor & heater setiap 6 bulan.</li>\n  <li>✔ Perawatan preventif oleh teknisi distributor minimal 1x per tahun.</li>\n</ul>\n\n<h4>Keunggulan Layanan Servis Kami:</h4>\n<ul>\n  <li>✔ Didukung teknisi bersertifikat distributor resmi.</li>\n  <li>✔ Penggunaan sparepart asli & bergaransi.</li>\n  <li>✔ Laporan servis lengkap untuk kebutuhan audit RS.</li>\n  <li>✔ Penanganan cepat untuk masalah darurat.</li>\n</ul>\n\n<p><strong>Catatan Penting:</strong><br>\nMengabaikan alarm dishwasher dapat mengurangi efisiensi cuci, meningkatkan konsumsi listrik/air, hingga berisiko merusak komponen utama.</p>",
      "TROLLY MAKAN NETAL DAN PEMANAS": "<h4>KATEGORI TROLLY MAKAN NETAL DAN PEMANAS</h4>\n<p><strong>Perawatan &amp; Troubleshooting Troli Distribusi Makanan dengan Pemanas</strong></p>\n<p>Troli distribusi makanan dengan pemanas berperan penting dalam menjaga suhu makanan tetap stabil selama proses distribusi di rumah sakit. Untuk memastikan performa dan keamanan alat, diperlukan pemeriksaan rutin dan penanganan tepat jika terjadi gangguan.</p>\n\n<h4>Permasalahan &amp; Solusi Umum Troli Pemanas:</h4>\n<ol>\n  <li><strong>Tidak Ada Listrik</strong>\n    <ul>\n      <li>Periksa kabel power, pastikan terhubung ke sumber listrik.</li>\n      <li>Jika fuse (sekring) putus, ganti dengan fuse baru (oleh Teknisi Distributor).</li>\n    </ul>\n  </li>\n  <li><strong>Lampu Indikator Tidak Menyala</strong>\n    <ul>\n      <li>Lampu Indikator Hijau Rusak: Ganti lampu baru (oleh Teknisi Distributor).</li>\n      <li>Lampu Indikator Oranye Rusak: Ganti lampu baru (oleh Teknisi Distributor).</li>\n    </ul>\n  </li>\n  <li><strong>Troli Tidak Panas</strong>\n    <ul>\n      <li>Cek elemen pemanas, jika putus atau rusak segera ganti (oleh Teknisi Distributor).</li>\n    </ul>\n  </li>\n  <li><strong>Termostat Rusak</strong>\n    <ul>\n      <li>Periksa termostat, ganti jika tidak berfungsi (oleh Teknisi Distributor).</li>\n    </ul>\n  </li>\n  <li><strong>Roda Sulit Berputar</strong>\n    <ul>\n      <li>Pastikan rem roda tidak terkunci.</li>\n      <li>Bersihkan rambut atau kotoran yang melilit roda.</li>\n      <li>Jika roda rusak atau aus, ganti roda baru (oleh Teknisi Distributor).</li>\n    </ul>\n  </li>\n  <li><strong>Pengunci Pintu Rusak</strong>\n    <ul>\n      <li>Ganti pengunci pintu dengan unit baru (oleh Teknisi Distributor).</li>\n    </ul>\n  </li>\n</ol>\n\n<h4>Rekomendasi Perawatan Berkala:</h4>\n<ul>\n  <li>✔ Cek kabel &amp; konektor listrik secara rutin.</li>\n  <li>✔ Bersihkan elemen pemanas dan area dalam troli setiap minggu.</li>\n  <li>✔ Periksa fungsi lampu indikator &amp; thermostat setiap bulan.</li>\n  <li>✔ Pelumasan roda &amp; pembersihan dari benda asing (rambut, debu).</li>\n  <li>✔ Pemeriksaan sistem pemanas &amp; komponen kelistrikan minimal 6 bulan sekali oleh teknisi resmi.</li>\n</ul>\n\n<h4>Keunggulan Layanan Kami:</h4>\n<ul>\n  <li>✔ Suku cadang original bergaransi.</li>\n  <li>✔ Teknisi resmi &amp; bersertifikat distributor.</li>\n  <li>✔ Layanan cepat untuk kebutuhan operasional rumah sakit.</li>\n  <li>✔ Laporan servis &amp; dokumentasi lengkap.</li>\n</ul>\n\n<p><strong>Catatan:</strong><br>Perawatan rutin akan memperpanjang usia troli, menjaga keamanan makanan, serta memenuhi standar higienitas dan keselamatan distribusi di lingkungan rumah sakit.</p>"
    }
  },
  {
    "id": "kulkas-chiller-&-freezer",
    "title": "Troubleshooting Kulkas Chiller & Freezer",
    "katogori": ["Troubleshooting"],
    "subtitle": [],
    "description": {
      "Troubleshooting" : "<ol>\n  <li><strong>Tidak Ada Listrik/Power</strong>\n    <ul>\n      <li>Cek kabel listrik, pastikan terhubung ke sumber daya.</li>\n      <li>Kabel putus: ganti kabel (Teknisi Distributor).</li>\n      <li>Display panel mati: ganti display (Teknisi Distributor).</li>\n      <li>Tombol ON/OFF rusak: ganti baru (Teknisi Distributor).</li>\n    </ul>\n  </li>\n\n  <li><strong>Kompresor Tidak Berfungsi</strong>\n    <ul>\n      <li>Cek tegangan listrik, jika tidak stabil pasang stabilizer.</li>\n      <li>Kompresor rusak: ganti kompresor (Teknisi Distributor).</li>\n    </ul>\n  </li>\n\n  <li><strong>Kipas Evaporator Tidak Berfungsi</strong>\n    <ul>\n      <li>Motor fan rusak: ganti baru (Teknisi Distributor).</li>\n      <li>Tidak ada tegangan listrik (periksa teknisi).</li>\n      <li>Kapasitor rusak: ganti baru (Teknisi Distributor).</li>\n    </ul>\n  </li>\n\n  <li><strong>Temperatur Panas/Tidak Sesuai Pengaturan</strong>\n    <ul>\n      <li>Overload rusak: ganti baru (Teknisi Distributor).</li>\n      <li>Pintu sering dibuka/tidak rapat: edukasi pengguna.</li>\n      <li>Suhu ruangan &gt; 38°C: tambahkan sirkulasi udara (kipas/AC).</li>\n      <li>Relay terbakar/konslet: ganti baru (Teknisi Distributor).</li>\n      <li>Freon bocor: perbaikan kebocoran (Teknisi Distributor).</li>\n    </ul>\n  </li>\n\n  <li><strong>Bunga Es (Ice Blocking)</strong>\n    <ul>\n      <li>Isi kulkas melebihi kapasitas: edukasi pengguna.</li>\n      <li>Lokasi terlalu lembap: pindahkan ke area kering.</li>\n      <li>Fan evaporator rusak: ganti baru (Teknisi Distributor).</li>\n      <li>Pintu terbuka lama: edukasi pengguna.</li>\n    </ul>\n  </li>\n\n  <li><strong>Error Display (E1, E2, Hi, Lo, Cl)</strong>\n    <ul>\n      <li>Control panel rusak: ganti panel baru (Teknisi Distributor).</li>\n    </ul>\n  </li>\n</ol>"
    }
  },
  {
    "id": "servis-open-&-steamer",
    "title": "Servis Open & Steamer",
    "katogori": ["Servis Open"],
    "subtitle": [],
    "description": {
      "Servis Open": "<ol>\n  <li><strong>1. Penggantian Elemen Pemanas</strong>\n    <h5>Gejala Umum:</h5>\n    <ul>\n      <li>Tidak panas atau suhu tidak naik.</li>\n      <li>Pemanasan tidak merata.</li>\n    </ul>\n    <h5>Tindakan:</h5>\n    <ul>\n      <li>Cek koneksi listrik ke elemen pemanas.</li>\n      <li>Ukur resistansi elemen menggunakan multitester (pastikan sesuai spesifikasi).</li>\n      <li>Jika elemen putus/rusak: Ganti elemen pemanas baru.</li>\n      <li>Pastikan pemasangan elemen baru rapat &amp; aman, hindari hubungan arus pendek.</li>\n      <li>Tes kembali fungsi pemanasan setelah penggantian.</li>\n    </ul>\n    <p><strong>Catatan:</strong><br>\n    Penggantian hanya boleh dilakukan oleh teknisi berpengalaman untuk menghindari kerusakan pada wiring atau thermostat.</p>\n  </li>\n\n  <li><strong>2. Perbaikan Sistem Digital (Panel Kontrol Digital)</strong>\n    <h5>Gejala Umum:</h5>\n    <ul>\n      <li>Layar panel mati/tidak tampil.</li>\n      <li>Tampil error code (misal E1, E2, dll).</li>\n      <li>Tombol digital tidak berfungsi.</li>\n    </ul>\n    <h5>Tindakan:</h5>\n    <ul>\n      <li>Cek suplai listrik ke control panel.</li>\n      <li>Pastikan PCB (Printed Circuit Board) dalam kondisi baik, tidak ada komponen terbakar atau jalur putus.</li>\n      <li>Jika ada kerusakan komponen (misalnya relay, IC, resistor): lakukan penggantian komponen.</li>\n      <li>Jika kerusakan parah/tidak bisa diperbaiki: Ganti unit control panel digital secara keseluruhan.</li>\n      <li>Lakukan reset sistem jika tersedia di manual.</li>\n      <li>Tes seluruh fungsi panel (setting suhu, timer, steam, dll).</li>\n    </ul>\n    <p><strong>Catatan:</strong><br>\n    Perbaikan sistem digital memerlukan alat khusus seperti multitester, solder station, dan kadang software reset tertentu.</p>\n  </li>\n</ol>\n\n<h4>Peringatan Umum:</h4>\n<ul>\n  <li>Cabut listrik sebelum servis.</li>\n  <li>Gunakan sparepart original dari pabrikan.</li>\n  <li>Servis digital &amp; elemen pemanas wajib dilakukan teknisi berlisensi untuk menghindari risiko korsleting atau malfungsi.</li>\n</ul>"
    }
  },
  {
    "id": "penjualan-sparepart",
    "title": "Penjualan Sparepart & Layanan Purna Jual Resmi Peralatan Dapur Rumah Sakit",
    "katogori": ["Sparepart"],
    "subtitle": [],
    "description": {
      "Sparepart": "<p>Kami menyediakan layanan penjualan sparepart resmi dan bergaransi untuk seluruh peralatan dapur rumah sakit, mulai dari oven, steamer, chiller, freezer, hingga cooking range dan peralatan kitchen lainnya.</p>\n<p>Semua sparepart yang kami jual adalah original dari pabrikan, dijamin kompatibel dan berkualitas sesuai standar industri foodservice untuk rumah sakit.</p>\n\n<h4>Katalog Sparepart Lengkap:</h4>\n<ul>\n  <li>Tersedia berbagai kategori sparepart:\n    <ul>\n      <li>Elemen Pemanas (heater)</li>\n      <li>Thermocouple</li>\n      <li>Burner &amp; Spuyer</li>\n      <li>Kipas Evaporator &amp; Motor Fan</li>\n      <li>Sensor &amp; Thermostat</li>\n      <li>Display Panel Digital</li>\n      <li>Kabel, Relay, Modul Kontrol</li>\n      <li>Kunci, Engsel, Gasket Pintu, dll.</li>\n    </ul>\n  </li>\n  <li>Dilengkapi gambar produk, kode sparepart, spesifikasi teknis, dan keterangan kecocokan unit.</li>\n</ul>\n\n<h4>Layanan Purna Jual Bergaransi:</h4>\n<ul>\n  <li><strong>Garansi Resmi Sparepart:</strong><br>Semua sparepart dilengkapi garansi resmi dari pabrikan (6-12 bulan, tergantung jenis barang).</li>\n  <li><strong>Layanan Perbaikan &amp; Penggantian:</strong><br>Dikerjakan oleh teknisi resmi &amp; bersertifikasi, meliputi:\n    <ul>\n      <li>Penggantian elemen pemanas</li>\n      <li>Perbaikan digital panel</li>\n      <li>Perbaikan mekanik &amp; kelistrikan</li>\n    </ul>\n  </li>\n  <li><strong>Klaim Garansi Mudah:</strong><br>Melalui form online atau kontak service center resmi kami.</li>\n  <li><strong>Dukungan After Sales:</strong>\n    <ul>\n      <li>Konsultasi pemilihan sparepart</li>\n      <li>Jadwal pemasangan di lokasi rumah sakit</li>\n      <li>Laporan teknis &amp; dokumentasi servis</li>\n    </ul>\n  </li>\n</ul>\n\n<h4>Keunggulan Layanan Kami:</h4>\n<ul>\n  <li>✔ Sparepart Original &amp; Bersertifikat</li>\n  <li>✔ Tim Teknisi Berpengalaman di Peralatan Dapur Rumah Sakit</li>\n  <li>✔ Garansi Resmi &amp; Dukungan Purna Jual</li>\n  <li>✔ Katalog Lengkap, Update, &amp; Mudah Diakses</li>\n  <li>✔ Respon Cepat untuk Kebutuhan Darurat</li>\n</ul>\n\n<p><a href=\"https://jadibener.com/spare-part\" target=\"_blank\">Lihat katalog lengkap di sini</a></p>"
    }
  },
  {
    "id" : "maintenance-&-instalasi-sistem-gas",
    "title": "Maintenance & Instalasi Sistem Gas: Menjamin Keamanan dan Performa Optimal",
    "katogori": ["Sistem Gas"],
    "subtitle": [],
    "description": {
      "Sistem Gas": "<p>Sistem gas pada dapur industri, termasuk dapur rumah sakit, memiliki peran vital untuk mendukung kelancaran operasional harian. Untuk itu, instalasi yang tepat serta maintenance berkala menjadi keharusan guna menjamin keamanan, efisiensi, dan usia pakai peralatan.</p>\n\n<h4>Layanan Instalasi Sistem Gas:</h4>\n<ul>\n  <li>Desain &amp; Instalasi Pipa Gas Sentral &amp; Tabung sesuai standar SNI.</li>\n  <li>Pemasangan Regulator, Pressure Gauge, Safety Valve, dan Shut-Off Valve.</li>\n  <li>Uji fungsi dan tes kebocoran awal untuk memastikan seluruh sambungan gas aman digunakan.</li>\n  <li>Penyediaan dokumentasi instalasi dan sertifikasi instalasi gas (jika dibutuhkan).</li>\n</ul>\n\n<h4>Pengecekan Keamanan Berkala:</h4>\n<ul>\n  <li>Pemeriksaan Tekanan Gas (via pressure gauge) untuk memastikan stabilitas aliran.</li>\n  <li>Cek Kondisi Pipa &amp; Selang (tidak retak, tidak bocor, tidak berkarat).</li>\n  <li>Uji Kebocoran Gas menggunakan metode air sabun di seluruh sambungan.</li>\n  <li>Pengecekan fungsi stop kran utama dan katup darurat.</li>\n  <li>Verifikasi kondisi regulator dan sistem alarm kebocoran (jika ada).</li>\n</ul>\n\n<h4>Perawatan Berkala (Preventive Maintenance):</h4>\n<ul>\n  <li>Pembersihan Komponen Burner &amp; Spuyer agar pembakaran optimal.</li>\n  <li>Penggantian regulator, selang, atau valve bila sudah melewati usia pakai.</li>\n  <li>Kalibrasi ulang alat pengukur tekanan.</li>\n  <li>Pemeriksaan sistem ventilasi dapur untuk memastikan sirkulasi udara memadai.</li>\n  <li>Laporan inspeksi tertulis sebagai bukti kelayakan operasional.</li>\n</ul>\n\n<h4>Keunggulan Layanan Kami:</h4>\n<ul>\n  <li>✔ Tenaga teknisi tersertifikasi</li>\n  <li>✔ Menggunakan alat deteksi kebocoran gas standar industri</li>\n  <li>✔ SOP keamanan mengacu pada standar K3 &amp; SNI</li>\n  <li>✔ Layanan cepat untuk perawatan darurat atau kebutuhan audit</li>\n  <li>✔ Memberikan edukasi singkat kepada pengguna akhir di lokasi</li>\n</ul>\n\n<h4>Rekomendasi Jadwal Maintenance:</h4>\n<ul>\n  <li>Inspeksi Minor: setiap 3 bulan</li>\n  <li>Maintenance Lengkap &amp; Kalibrasi: setiap 6-12 bulan</li>\n  <li>Penggantian Regulator &amp; Selang: sesuai rekomendasi pabrikan atau maksimal 2 tahun penggunaan</li>\n</ul>\n\n<p><strong>Ingat!</strong> Sistem gas yang terawat tidak hanya menjaga kelancaran operasional, tetapi juga menghindarkan risiko kecelakaan kerja, kebakaran, dan kerusakan alat berat.</p>"
    }
  },
  {
    "id" : "pembersihan-&-servis-hood-dapur",
    "title": "Pembersihan & Servis Hood Dapur: Menjaga Kebersihan, Kinerja, dan Keamanan Dapur Industri",
    "katogori": ["Pembersihan"],
    "subtitle": [],
    "description": {
      "Pembersihan": "<p>Sistem hood (penyedot asap) pada dapur industri, terutama di dapur rumah sakit, memiliki peran penting dalam menjaga kualitas udara, mengurangi risiko kebakaran, serta memastikan kenyamanan dan keselamatan lingkungan kerja.</p>\n<p>Tanpa perawatan rutin, tumpukan minyak, debu, dan partikel pembakaran dapat menyumbat ducting, menurunkan performa kipas, hingga memicu potensi kebakaran serius.</p>\n\n<h4>Layanan Pembersihan &amp; Servis Hood:</h4>\n<ol>\n  <li><strong>Pembersihan Hood &amp; Saluran Ducting</strong>\n    <ul>\n      <li>Membersihkan permukaan dalam &amp; luar hood dari lemak dan jelaga.</li>\n      <li>Menyikat dan menyedot kotoran di sepanjang saluran ducting (dari inlet hingga outlet).</li>\n      <li>Penyemprotan degreaser food grade untuk mengangkat sisa minyak membandel.</li>\n      <li>Pemeriksaan dan pembersihan filter hood (grease filter atau carbon filter).</li>\n    </ul>\n  </li>\n  <li><strong>Servis &amp; Penggantian Kipas Hood</strong>\n    <ul>\n      <li>Cek performa motor fan &amp; baling-baling (blade).</li>\n      <li>Membersihkan baling-baling dari kotoran yang dapat mengganggu putaran kipas.</li>\n      <li>Lubrikasi bearing motor fan untuk menghindari keausan.</li>\n      <li>Penggantian motor fan/kipas jika putaran melemah, berisik, atau rusak.</li>\n      <li>Pengujian hisapan udara untuk memastikan daya serap maksimal setelah servis.</li>\n    </ul>\n  </li>\n  <li><strong>Inspeksi Saluran Ducting &amp; Sistem Ventilasi</strong>\n    <ul>\n      <li>Deteksi adanya kebocoran, keretakan, atau sambungan yang longgar di ducting.</li>\n      <li>Cek isolasi ducting untuk menghindari kondensasi dan penurunan suhu.</li>\n      <li>Validasi arah aliran udara dan output udara buangan agar memenuhi standar K3 &amp; lingkungan.</li>\n    </ul>\n  </li>\n</ol>\n\n<h4>Manfaat Perawatan Rutin:</h4>\n<ul>\n  <li>✔ Menghindari akumulasi lemak penyebab risiko kebakaran</li>\n  <li>✔ Menjaga kinerja optimal sistem ventilasi</li>\n  <li>✔ Meningkatkan efisiensi listrik (kipas bekerja lebih ringan)</li>\n  <li>✔ Memperpanjang usia pakai motor fan &amp; ducting</li>\n  <li>✔ Menjamin kualitas udara dapur bersih &amp; bebas asap berbahaya</li>\n</ul>\n\n<h4>Jadwal Rekomendasi Servis:</h4>\n<ul>\n  <li>Pembersihan Minor Hood &amp; Filter: 1 bulan sekali</li>\n  <li>Pembersihan Total Hood &amp; Ducting: 6 bulan – 1 tahun sekali (tergantung intensitas pemakaian)</li>\n  <li>Inspeksi &amp; Servis Kipas: 6 bulan sekali atau jika muncul suara abnormal</li>\n</ul>\n\n<h4>Keunggulan Layanan Kami:</h4>\n<ul>\n  <li>✔ Tim profesional &amp; berpengalaman</li>\n  <li>✔ Menggunakan alat vakum industrial &amp; chemical food grade</li>\n  <li>✔ Laporan foto before-after setiap pembersihan</li>\n  <li>✔ Sertifikat pembersihan untuk keperluan audit K3 Rumah Sakit</li>\n  <li>✔ Layanan penggantian sparepart original (motor fan, filter, dll.)</li>\n</ul>\n\n<p><strong>Catatan:</strong><br>\nPerawatan menyeluruh tidak hanya melindungi peralatan mahal, tetapi juga memenuhi standar keselamatan industri (K3) yang diwajibkan untuk dapur fasilitas publik seperti rumah sakit.</p>"
    }
  }
]